studsar.py
managers/manager.py
models/__init__.py
models/neural.py
rag/__init__.py
rag/rag_connector.py
utils/__init__.py
utils/text.py
studsar_ai-0.1.3.dist-info/METADATA
studsar_ai-0.1.3.dist-info/WHEEL
studsar_ai-0.1.3.dist-info/top_level.txt
studsar_ai-0.1.3.dist-info/RECORD
