Metadata-Version: 2.4
Name: studsar-ai
Version: 0.1.3
Summary: StudSAR AI RAG evaluation and neural retrieval toolkit
Author: Valentina Ewelu
Maintainer: Valentina Ewelu
Requires-Python: >=3.9
Requires-Dist: sentence-transformers
Requires-Dist: numpy
Requires-Dist: torch
Requires-Dist: transformers>=4.40
Requires-Dist: scikit-learn
Requires-Dist: networkx
Requires-Dist: matplotlib
Requires-Dist: langchain-community
Requires-Dist: langchain-core
Requires-Dist: pypdf
Requires-Dist: beautifulsoup4
Requires-Dist: gradio
